{"version": 0.6, "generator": "Overpass API 0.7.62.5 1bd436f1", "osm3s": {"timestamp_osm_base": "2025-04-09T14:27:00Z", "copyright": "The data included in this document is from www.openstreetmap.org. The data is made available under ODbL."}, "elements": [{"type": "node", "id": 3028358959, "lat": 36.2327663, "lon": 1.7123653, "tags": {"name": "Sidi Bouabida", "public_transport": "station", "railway": "station", "train": "yes", "wikidata": "Q118134343", "wikipedia": "fr:Gare de Sidi Bouabia"}}, {"type": "node", "id": 3028366156, "lat": 36.2254897, "lon": 1.6693083, "tags": {"name": "El Attaf", "name:ar": "\u0627\u0644\u0639\u0637\u0627\u0641", "name:en": "El Attaf", "name:fr": "El Attaf", "operator": "SNTF", "public_transport": "station", "railway": "station", "wikidata": "Q118134336", "wikipedia": "fr:Gare d'El Attaf"}}, {"type": "node", "id": 3155254758, "lat": 36.2417811, "lon": 1.8068677, "tags": {"bench": "yes", "bus": "yes", "highway": "bus_stop", "name": "\u0645\u062d\u0637\u0629 \u0627\u0644\u062d\u0627\u0641\u0644\u0627\u062a", "name:ar": "\u0645\u062d\u0637\u0629 \u0627\u0644\u062d\u0627\u0641\u0644\u0627\u062a", "name:fr": "Bus", "operator": "Op\u00e9rateurs priv\u00e9s", "public_transport": "stop_position", "shelter": "yes"}}, {"type": "node", "id": 3202416344, "lat": 36.1573816, "lon": 1.8200272, "tags": {"bus": "yes", "highway": "bus_stop", "public_transport": "platform"}}, {"type": "node", "id": 4438875988, "lat": 36.2429803, "lon": 1.9223552, "tags": {"bus": "yes", "highway": "bus_stop", "name": "Arr\u00eat Mazouni", "public_transport": "platform", "shelter": "yes"}}, {"type": "node", "id": 4438876073, "lat": 36.2538536, "lon": 1.9525768, "tags": {"bench": "yes", "bin": "yes", "bus": "yes", "covered": "no", "departures_board": "no", "highway": "bus_stop", "name": "Arr\u00eat El-khadhar", "name:arq": "\u0645\u0648\u0642\u0641 \u0627\u0644\u062e\u0636\u0651\u0627\u0631", "public_transport": "stop_position", "shelter": "yes", "tactile_paving": "no"}}, {"type": "node", "id": 4438876079, "lat": 36.2218576, "lon": 1.9129901, "tags": {"bus": "yes", "highway": "bus_stop", "name:ar": "\u062d\u0633\u0627\u0646", "name:fr": "Arr\u00eat Hassan", "public_transport": "platform"}}, {"type": "node", "id": 4438876148, "lat": 36.2215632, "lon": 1.9132269, "tags": {"bus": "yes", "highway": "bus_stop", "name:ar": "\u062d\u0633\u0627\u0646", "name:fr": "Arr\u00eat Hassan", "public_transport": "platform"}}, {"type": "node", "id": 4655493298, "lat": 36.2305995, "lon": 1.7194958, "tags": {"bus": "yes", "highway": "bus_stop", "name": "\u0645\u062d\u0637\u0629 \u0633\u064a\u062f\u064a \u0628\u0648\u0639\u0628\u064a\u062f\u0629", "name:ar": "\u0645\u062d\u0637\u0629 \u0633\u064a\u062f\u064a \u0628\u0648\u0639\u0628\u064a\u062f\u0629", "name:fr": "Sidi Bouabida", "public_transport": "platform"}}, {"type": "node", "id": 5168850775, "lat": 36.2405282, "lon": 1.8148622, "tags": {"bench": "no", "bus": "yes", "highway": "bus_stop", "name": "\u0645\u0648\u0642\u0641 \u0627\u0644\u062b\u0627\u0646\u0648\u064a\u0629", "name:ar": "\u0645\u0648\u0642\u0641 \u0627\u0644\u062b\u0627\u0646\u0648\u064a\u0629", "name:en": "High school bus stop", "name:fr": "Arr\u00eat du lyc\u00e9e", "public_transport": "platform", "shelter": "no"}}, {"type": "node", "id": 5168850780, "lat": 36.241478, "lon": 1.8066186, "tags": {"bench": "yes", "bin": "yes", "bus": "yes", "covered": "no", "highway": "bus_stop", "name": "\u0645\u062d\u0637\u0629 \u0627\u0644\u062d\u0627\u0641\u0644\u0627\u062a", "name:ar": "\u0645\u062d\u0637\u0629 \u0627\u0644\u062d\u0627\u0641\u0644\u0627\u062a", "name:fr": "Bus", "public_transport": "stop_position", "shelter": "yes", "tactile_paving": "no"}}, {"type": "node", "id": 11433461969, "lat": 36.2430478, "lon": 1.9220486, "tags": {"highway": "bus_stop", "name": "\u0645\u0648\u0642\u0641 \u062d\u0627\u0641\u0644\u0629 \u0645\u0627\u0632\u0648\u0646\u064a", "name:fr": "Arr\u00eat Mazouni"}}, {"type": "node", "id": 12532183259, "lat": 36.253918, "lon": 1.9523233, "tags": {"bench": "yes", "bus": "yes", "highway": "bus_stop", "name": "Arr\u00eat El-khadhar", "name:arq": "\u0645\u0648\u0642\u0641 \u0627\u0644\u062e\u0636\u0651\u0627\u0631", "public_transport": "stop_position", "shelter": "yes"}}]}